my_python_library/__init__.py
my_python_library/example.py
somanath_python_library-0.1.0.dist-info/METADATA
somanath_python_library-0.1.0.dist-info/WHEEL
somanath_python_library-0.1.0.dist-info/RECORD
